sam_mask_cli/__init__.py
sam_mask_cli/cli.py
sam_mask_cli-0.1.1.dist-info/METADATA
sam_mask_cli-0.1.1.dist-info/WHEEL
sam_mask_cli-0.1.1.dist-info/entry_points.txt
sam_mask_cli-0.1.1.dist-info/licenses/LICENSE
sam_mask_cli-0.1.1.dist-info/RECORD
