Metadata-Version: 2.4
Name: sam-mask-cli
Version: 0.1.1
Summary: A command-line tool for generating segmentation masks using SAM (Segment Anything Model)
Project-URL: Homepage, https://github.com/yourusername/sam-mask-cli
Project-URL: Repository, https://github.com/yourusername/sam-mask-cli
Project-URL: Issues, https://github.com/yourusername/sam-mask-cli/issues
Author-email: Adam Barbato <adambarbato94@gmail.com>
License-Expression: MIT
License-File: LICENSE
Keywords: cli,computer-vision,mask,sam,segmentation,ultralytics
Classifier: Development Status :: 4 - Beta
Classifier: Intended Audience :: Developers
Classifier: License :: OSI Approved :: MIT License
Classifier: Programming Language :: Python :: 3
Classifier: Programming Language :: Python :: 3.10
Classifier: Programming Language :: Python :: 3.11
Classifier: Programming Language :: Python :: 3.12
Classifier: Topic :: Scientific/Engineering :: Image Processing
Classifier: Topic :: Software Development :: Libraries :: Python Modules
Requires-Python: >=3.10
Requires-Dist: matplotlib>=3.10.7
Requires-Dist: numpy>=2.2.6
Requires-Dist: opencv-python>=4.11.0.86
Requires-Dist: torch>=2.9.0
Requires-Dist: ultralytics>=8.3.218
Provides-Extra: dev
Requires-Dist: black>=23.0; extra == 'dev'
Requires-Dist: flake8>=6.0; extra == 'dev'
Requires-Dist: isort>=5.0; extra == 'dev'
Requires-Dist: mypy>=1.0; extra == 'dev'
Requires-Dist: pytest>=7.0; extra == 'dev'
